qopt/__init__.py
qopt/amplitude_functions.py
qopt/analyser.py
qopt/cost_functions.py
qopt/data_container.py
qopt/energy_spectrum.py
qopt/matrix.py
qopt/noise.py
qopt/optimization_data.py
qopt/optimize.py
qopt/performance_statistics.py
qopt/simulator.py
qopt/solver_algorithms.py
qopt/transfer_function.py
qopt/util.py
quantum_computer-0.1.dist-info/LICENSE
quantum_computer-0.1.dist-info/METADATA
quantum_computer-0.1.dist-info/WHEEL
quantum_computer-0.1.dist-info/top_level.txt
quantum_computer-0.1.dist-info/RECORD
